odoo/addons/website_media_size/README.rst
odoo/addons/website_media_size/__init__.py
odoo/addons/website_media_size/__manifest__.py
odoo/addons/website_media_size/i18n/ca.po
odoo/addons/website_media_size/i18n/es.po
odoo/addons/website_media_size/i18n/fr.po
odoo/addons/website_media_size/i18n/it.po
odoo/addons/website_media_size/i18n/pt_BR.po
odoo/addons/website_media_size/i18n/website_media_size.pot
odoo/addons/website_media_size/readme/CONTRIBUTORS.rst
odoo/addons/website_media_size/readme/DESCRIPTION.rst
odoo/addons/website_media_size/readme/USAGE.rst
odoo/addons/website_media_size/static/description/icon.png
odoo/addons/website_media_size/static/description/index.html
odoo/addons/website_media_size/static/description/screenshot.png
odoo/addons/website_media_size/static/src/js/website_media_size.js
odoo/addons/website_media_size/static/src/scss/website_media_size.scss
odoo/addons/website_media_size/static/src/xml/website_media_size.xml
odoo/addons/website_media_size/templates/assets.xml
odoo12_addon_website_media_size-12.0.1.0.0.99.dev16.dist-info/METADATA
odoo12_addon_website_media_size-12.0.1.0.0.99.dev16.dist-info/WHEEL
odoo12_addon_website_media_size-12.0.1.0.0.99.dev16.dist-info/top_level.txt
odoo12_addon_website_media_size-12.0.1.0.0.99.dev16.dist-info/RECORD
